CommonCrawlJob-0.1.0.dist-info/DESCRIPTION.rst
CommonCrawlJob-0.1.0.dist-info/METADATA
CommonCrawlJob-0.1.0.dist-info/RECORD
CommonCrawlJob-0.1.0.dist-info/WHEEL
CommonCrawlJob-0.1.0.dist-info/entry_points.txt
CommonCrawlJob-0.1.0.dist-info/metadata.json
CommonCrawlJob-0.1.0.dist-info/top_level.txt
CommonCrawlJob-0.1.0.dist-info/zip-safe
aws/__init__.py
aws/__main__.py
aws/aws.py
aws/redshift.py
ccjob/__init__.py
ccjob/__version__.py
ccjob/commoncrawl.py
ccjob/config.py
ccjob/gzipstream.py
ccjob/structures.py
