Metadata-Version: 2.0
Name: CommonCrawlJob
Version: 0.1.0
Summary: Extract data from common crawl using elastic map reduce
Home-page: https://github.com/qadium-memex/CommonCrawlJob
Author: Qadium Inc
Author-email: sang@qadium.com
License: Apache Software License v2
Platform: UNKNOWN
Classifier: Development Status :: 3 - Alpha
Classifier: Environment :: Console
Classifier: Intended Audience :: Developers
Classifier: Natural Language :: English
Classifier: License :: OSI Approved :: Apache Software License
Classifier: Operating System :: OS Independent
Classifier: Programming Language :: Unix Shell
Classifier: Programming Language :: Python
Classifier: Programming Language :: Python :: 2.7
Classifier: Topic :: Software Development :: Libraries :: Python Modules
Classifier: Topic :: Text Processing :: Linguistic
Classifier: Topic :: Utilities
Requires-Dist: warc
